fish_speech_lib/__init__.py
fish_speech_lib/config.py
fish_speech_lib/inference.py
fish_speech_lib/model.py
fish_speech_lib/utils.py
fish_speech_lib/fish_speech/__init__.py
fish_speech_lib/fish_speech/conversation.py
fish_speech_lib/fish_speech/scheduler.py
fish_speech_lib/fish_speech/tokenizer.py
fish_speech_lib/fish_speech/callbacks/__init__.py
fish_speech_lib/fish_speech/callbacks/grad_norm.py
fish_speech_lib/fish_speech/inference_engine/__init__.py
fish_speech_lib/fish_speech/inference_engine/reference_loader.py
fish_speech_lib/fish_speech/inference_engine/utils.py
fish_speech_lib/fish_speech/inference_engine/vq_manager.py
fish_speech_lib/fish_speech/models/text2semantic/__init__.py
fish_speech_lib/fish_speech/models/text2semantic/inference.py
fish_speech_lib/fish_speech/models/text2semantic/lit_module.py
fish_speech_lib/fish_speech/models/text2semantic/llama.py
fish_speech_lib/fish_speech/models/text2semantic/lora.py
fish_speech_lib/fish_speech/models/vqgan/__init__.py
fish_speech_lib/fish_speech/models/vqgan/inference.py
fish_speech_lib/fish_speech/models/vqgan/utils.py
fish_speech_lib/fish_speech/models/vqgan/modules/__init__.py
fish_speech_lib/fish_speech/models/vqgan/modules/firefly.py
fish_speech_lib/fish_speech/models/vqgan/modules/fsq.py
fish_speech_lib/fish_speech/text/__init__.py
fish_speech_lib/fish_speech/text/clean.py
fish_speech_lib/fish_speech/text/spliter.py
fish_speech_lib/fish_speech/utils/__init__.py
fish_speech_lib/fish_speech/utils/braceexpand.py
fish_speech_lib/fish_speech/utils/context.py
fish_speech_lib/fish_speech/utils/file.py
fish_speech_lib/fish_speech/utils/instantiators.py
fish_speech_lib/fish_speech/utils/logger.py
fish_speech_lib/fish_speech/utils/logging_utils.py
fish_speech_lib/fish_speech/utils/rich_utils.py
fish_speech_lib/fish_speech/utils/schema.py
fish_speech_lib/fish_speech/utils/spectrogram.py
fish_speech_lib/fish_speech/utils/utils.py
fish_speech_lib-0.1.0.1.dist-info/licenses/LICENSE
fish_speech_lib-0.1.0.1.dist-info/METADATA
fish_speech_lib-0.1.0.1.dist-info/WHEEL
fish_speech_lib-0.1.0.1.dist-info/entry_points.txt
fish_speech_lib-0.1.0.1.dist-info/top_level.txt
fish_speech_lib-0.1.0.1.dist-info/RECORD
