Metadata-Version: 2.4
Name: fish_speech_lib
Version: 0.1.0.1
Summary: Fish Speech pipeline as library so you don't need to webui.
Author-email: Atm4x <bloodyseiko@gmail.com>
License:                                  Apache License
Project-URL: Homepage, https://github.com/Atm4x/Fish-speech-pipeline
Project-URL: Repository, https://github.com/Atm4x/Fish-speech-pipeline
Project-URL: Bug Tracker, https://github.com/Atm4x/Fish-speech-pipeline/issues
Project-URL: Original Project, https://github.com/fishaudio/fish-speech
Keywords: tts,text-to-speech,voice-cloning,llama,speech-synthesis,fish-speech,Atm4x,fish audio
Classifier: Programming Language :: Python :: 3
Classifier: License :: OSI Approved :: Apache Software License
Classifier: Operating System :: OS Independent
Requires-Python: >=3.8
License-File: LICENSE
Requires-Dist: numpy<=1.26.4
Requires-Dist: natsort>=8.4.0
Requires-Dist: transformers>=4.45.2
Requires-Dist: datasets==2.18.0
Requires-Dist: lightning>=2.1.0
Requires-Dist: hydra-core>=1.3.2
Requires-Dist: tensorboard>=2.14.1
Requires-Dist: einops>=0.7.0
Requires-Dist: librosa>=0.9.1
Requires-Dist: rich>=13.5.3
Requires-Dist: wandb>=0.15.11
Requires-Dist: grpcio>=1.58.0
Requires-Dist: kui>=1.6.0
Requires-Dist: uvicorn>=0.30.0
Requires-Dist: loguru>=0.6.0
Requires-Dist: pyrootutils>=1.0.4
Requires-Dist: resampy>=0.4.3
Requires-Dist: zstandard>=0.22.0
Requires-Dist: pydub
Requires-Dist: pyaudio
Requires-Dist: faster-whisper
Requires-Dist: ormsgpack
Requires-Dist: tiktoken>=0.8.0
Requires-Dist: pydantic==2.9.2
Requires-Dist: cachetools
Requires-Dist: huggingface-hub
Requires-Dist: loralib
Requires-Dist: vector_quantize_pytorch==1.14.24
Dynamic: license-file
